{
  "id": "5f9a3bfd-e334-43d1-a311-87d1f3a7f2e1",
  "prevId": "26fac0e9-41ab-47e3-8e3e-c682ecdeb639",
  "version": "7",
  "dialect": "postgresql",
  "tables": {
    "public.committees": {
      "name": "committees",
      "schema": "",
      "columns": {
        "id": {
          "name": "id",
          "type": "uuid",
          "primaryKey": true,
          "notNull": true,
          "default": "gen_random_uuid()"
        },
        "conference_id": {
          "name": "conference_id",
          "type": "uuid",
          "primaryKey": false,
          "notNull": true
        },
        "name": {
          "name": "name",
          "type": "text",
          "primaryKey": false,
          "notNull": true
        },
        "type": {
          "name": "type",
          "type": "text",
          "primaryKey": false,
          "notNull": true
        },
        "topic": {
          "name": "topic",
          "type": "text",
          "primaryKey": false,
          "notNull": true,
          "default": "''"
        },
        "data": {
          "name": "data",
          "type": "jsonb",
          "primaryKey": false,
          "notNull": true
        },
        "version": {
          "name": "version",
          "type": "integer",
          "primaryKey": false,
          "notNull": true,
          "default": 0
        },
        "floor_migrated": {
          "name": "floor_migrated",
          "type": "boolean",
          "primaryKey": false,
          "notNull": true,
          "default": false
        },
        "scoring_migrated": {
          "name": "scoring_migrated",
          "type": "boolean",
          "primaryKey": false,
          "notNull": true,
          "default": false
        },
        "next_draft_submission_order": {
          "name": "next_draft_submission_order",
          "type": "integer",
          "primaryKey": false,
          "notNull": true,
          "default": 0
        },
        "created_at": {
          "name": "created_at",
          "type": "timestamp with time zone",
          "primaryKey": false,
          "notNull": true,
          "default": "now()"
        },
        "updated_at": {
          "name": "updated_at",
          "type": "timestamp with time zone",
          "primaryKey": false,
          "notNull": true,
          "default": "now()"
        }
      },
      "indexes": {},
      "foreignKeys": {
        "committees_conference_id_conferences_id_fk": {
          "name": "committees_conference_id_conferences_id_fk",
          "tableFrom": "committees",
          "tableTo": "conferences",
          "columnsFrom": [
            "conference_id"
          ],
          "columnsTo": [
            "id"
          ],
          "onDelete": "cascade",
          "onUpdate": "no action"
        }
      },
      "compositePrimaryKeys": {},
      "uniqueConstraints": {},
      "policies": {},
      "checkConstraints": {},
      "isRLSEnabled": false
    },
    "public.conferences": {
      "name": "conferences",
      "schema": "",
      "columns": {
        "id": {
          "name": "id",
          "type": "uuid",
          "primaryKey": true,
          "notNull": true,
          "default": "gen_random_uuid()"
        },
        "name": {
          "name": "name",
          "type": "text",
          "primaryKey": false,
          "notNull": true
        },
        "year": {
          "name": "year",
          "type": "integer",
          "primaryKey": false,
          "notNull": true
        },
        "created_at": {
          "name": "created_at",
          "type": "timestamp with time zone",
          "primaryKey": false,
          "notNull": true,
          "default": "now()"
        },
        "updated_at": {
          "name": "updated_at",
          "type": "timestamp with time zone",
          "primaryKey": false,
          "notNull": true,
          "default": "now()"
        }
      },
      "indexes": {},
      "foreignKeys": {},
      "compositePrimaryKeys": {},
      "uniqueConstraints": {},
      "policies": {},
      "checkConstraints": {},
      "isRLSEnabled": false
    },
    "public.delegates": {
      "name": "delegates",
      "schema": "",
      "columns": {
        "id": {
          "name": "id",
          "type": "uuid",
          "primaryKey": true,
          "notNull": true
        },
        "committee_id": {
          "name": "committee_id",
          "type": "uuid",
          "primaryKey": false,
          "notNull": true
        },
        "data": {
          "name": "data",
          "type": "jsonb",
          "primaryKey": false,
          "notNull": true
        },
        "version": {
          "name": "version",
          "type": "integer",
          "primaryKey": false,
          "notNull": true,
          "default": 0
        },
        "created_at": {
          "name": "created_at",
          "type": "timestamp with time zone",
          "primaryKey": false,
          "notNull": true,
          "default": "now()"
        }
      },
      "indexes": {
        "delegates_committee_idx": {
          "name": "delegates_committee_idx",
          "columns": [
            {
              "expression": "committee_id",
              "isExpression": false,
              "asc": true,
              "nulls": "last"
            },
            {
              "expression": "created_at",
              "isExpression": false,
              "asc": true,
              "nulls": "last"
            }
          ],
          "isUnique": false,
          "concurrently": false,
          "method": "btree",
          "with": {}
        }
      },
      "foreignKeys": {
        "delegates_committee_id_committees_id_fk": {
          "name": "delegates_committee_id_committees_id_fk",
          "tableFrom": "delegates",
          "tableTo": "committees",
          "columnsFrom": [
            "committee_id"
          ],
          "columnsTo": [
            "id"
          ],
          "onDelete": "cascade",
          "onUpdate": "no action"
        }
      },
      "compositePrimaryKeys": {},
      "uniqueConstraints": {},
      "policies": {},
      "checkConstraints": {},
      "isRLSEnabled": false
    },
    "public.documents": {
      "name": "documents",
      "schema": "",
      "columns": {
        "id": {
          "name": "id",
          "type": "uuid",
          "primaryKey": true,
          "notNull": true
        },
        "committee_id": {
          "name": "committee_id",
          "type": "uuid",
          "primaryKey": false,
          "notNull": true
        },
        "data": {
          "name": "data",
          "type": "jsonb",
          "primaryKey": false,
          "notNull": true
        },
        "submission_number": {
          "name": "submission_number",
          "type": "integer",
          "primaryKey": false,
          "notNull": false
        },
        "version": {
          "name": "version",
          "type": "integer",
          "primaryKey": false,
          "notNull": true,
          "default": 0
        },
        "created_at": {
          "name": "created_at",
          "type": "timestamp with time zone",
          "primaryKey": false,
          "notNull": true,
          "default": "now()"
        }
      },
      "indexes": {
        "documents_committee_idx": {
          "name": "documents_committee_idx",
          "columns": [
            {
              "expression": "committee_id",
              "isExpression": false,
              "asc": true,
              "nulls": "last"
            },
            {
              "expression": "created_at",
              "isExpression": false,
              "asc": true,
              "nulls": "last"
            }
          ],
          "isUnique": false,
          "concurrently": false,
          "method": "btree",
          "with": {}
        }
      },
      "foreignKeys": {
        "documents_committee_id_committees_id_fk": {
          "name": "documents_committee_id_committees_id_fk",
          "tableFrom": "documents",
          "tableTo": "committees",
          "columnsFrom": [
            "committee_id"
          ],
          "columnsTo": [
            "id"
          ],
          "onDelete": "cascade",
          "onUpdate": "no action"
        }
      },
      "compositePrimaryKeys": {},
      "uniqueConstraints": {},
      "policies": {},
      "checkConstraints": {},
      "isRLSEnabled": false
    },
    "public.motion_queue_history": {
      "name": "motion_queue_history",
      "schema": "",
      "columns": {
        "id": {
          "name": "id",
          "type": "uuid",
          "primaryKey": true,
          "notNull": true
        },
        "committee_id": {
          "name": "committee_id",
          "type": "uuid",
          "primaryKey": false,
          "notNull": true
        },
        "data": {
          "name": "data",
          "type": "jsonb",
          "primaryKey": false,
          "notNull": true
        },
        "created_at": {
          "name": "created_at",
          "type": "timestamp with time zone",
          "primaryKey": false,
          "notNull": true,
          "default": "now()"
        }
      },
      "indexes": {
        "motion_queue_history_committee_idx": {
          "name": "motion_queue_history_committee_idx",
          "columns": [
            {
              "expression": "committee_id",
              "isExpression": false,
              "asc": true,
              "nulls": "last"
            },
            {
              "expression": "created_at",
              "isExpression": false,
              "asc": true,
              "nulls": "last"
            }
          ],
          "isUnique": false,
          "concurrently": false,
          "method": "btree",
          "with": {}
        }
      },
      "foreignKeys": {
        "motion_queue_history_committee_id_committees_id_fk": {
          "name": "motion_queue_history_committee_id_committees_id_fk",
          "tableFrom": "motion_queue_history",
          "tableTo": "committees",
          "columnsFrom": [
            "committee_id"
          ],
          "columnsTo": [
            "id"
          ],
          "onDelete": "cascade",
          "onUpdate": "no action"
        }
      },
      "compositePrimaryKeys": {},
      "uniqueConstraints": {},
      "policies": {},
      "checkConstraints": {},
      "isRLSEnabled": false
    },
    "public.motions": {
      "name": "motions",
      "schema": "",
      "columns": {
        "id": {
          "name": "id",
          "type": "uuid",
          "primaryKey": true,
          "notNull": true
        },
        "committee_id": {
          "name": "committee_id",
          "type": "uuid",
          "primaryKey": false,
          "notNull": true
        },
        "data": {
          "name": "data",
          "type": "jsonb",
          "primaryKey": false,
          "notNull": true
        },
        "session_state": {
          "name": "session_state",
          "type": "jsonb",
          "primaryKey": false,
          "notNull": true,
          "default": "'{}'::jsonb"
        },
        "version": {
          "name": "version",
          "type": "integer",
          "primaryKey": false,
          "notNull": true,
          "default": 0
        },
        "created_at": {
          "name": "created_at",
          "type": "timestamp with time zone",
          "primaryKey": false,
          "notNull": true,
          "default": "now()"
        }
      },
      "indexes": {
        "motions_committee_idx": {
          "name": "motions_committee_idx",
          "columns": [
            {
              "expression": "committee_id",
              "isExpression": false,
              "asc": true,
              "nulls": "last"
            },
            {
              "expression": "created_at",
              "isExpression": false,
              "asc": true,
              "nulls": "last"
            }
          ],
          "isUnique": false,
          "concurrently": false,
          "method": "btree",
          "with": {}
        }
      },
      "foreignKeys": {
        "motions_committee_id_committees_id_fk": {
          "name": "motions_committee_id_committees_id_fk",
          "tableFrom": "motions",
          "tableTo": "committees",
          "columnsFrom": [
            "committee_id"
          ],
          "columnsTo": [
            "id"
          ],
          "onDelete": "cascade",
          "onUpdate": "no action"
        }
      },
      "compositePrimaryKeys": {},
      "uniqueConstraints": {},
      "policies": {},
      "checkConstraints": {},
      "isRLSEnabled": false
    },
    "public.points": {
      "name": "points",
      "schema": "",
      "columns": {
        "id": {
          "name": "id",
          "type": "uuid",
          "primaryKey": true,
          "notNull": true
        },
        "committee_id": {
          "name": "committee_id",
          "type": "uuid",
          "primaryKey": false,
          "notNull": true
        },
        "data": {
          "name": "data",
          "type": "jsonb",
          "primaryKey": false,
          "notNull": true
        },
        "version": {
          "name": "version",
          "type": "integer",
          "primaryKey": false,
          "notNull": true,
          "default": 0
        },
        "created_at": {
          "name": "created_at",
          "type": "timestamp with time zone",
          "primaryKey": false,
          "notNull": true,
          "default": "now()"
        }
      },
      "indexes": {
        "points_committee_idx": {
          "name": "points_committee_idx",
          "columns": [
            {
              "expression": "committee_id",
              "isExpression": false,
              "asc": true,
              "nulls": "last"
            },
            {
              "expression": "created_at",
              "isExpression": false,
              "asc": true,
              "nulls": "last"
            }
          ],
          "isUnique": false,
          "concurrently": false,
          "method": "btree",
          "with": {}
        }
      },
      "foreignKeys": {
        "points_committee_id_committees_id_fk": {
          "name": "points_committee_id_committees_id_fk",
          "tableFrom": "points",
          "tableTo": "committees",
          "columnsFrom": [
            "committee_id"
          ],
          "columnsTo": [
            "id"
          ],
          "onDelete": "cascade",
          "onUpdate": "no action"
        }
      },
      "compositePrimaryKeys": {},
      "uniqueConstraints": {},
      "policies": {},
      "checkConstraints": {},
      "isRLSEnabled": false
    },
    "public.position_paper_scores": {
      "name": "position_paper_scores",
      "schema": "",
      "columns": {
        "id": {
          "name": "id",
          "type": "uuid",
          "primaryKey": true,
          "notNull": true,
          "default": "gen_random_uuid()"
        },
        "committee_id": {
          "name": "committee_id",
          "type": "uuid",
          "primaryKey": false,
          "notNull": true
        },
        "delegate_id": {
          "name": "delegate_id",
          "type": "text",
          "primaryKey": false,
          "notNull": true
        },
        "data": {
          "name": "data",
          "type": "jsonb",
          "primaryKey": false,
          "notNull": true
        },
        "version": {
          "name": "version",
          "type": "integer",
          "primaryKey": false,
          "notNull": true,
          "default": 0
        },
        "created_at": {
          "name": "created_at",
          "type": "timestamp with time zone",
          "primaryKey": false,
          "notNull": true,
          "default": "now()"
        }
      },
      "indexes": {
        "position_paper_scores_unique_idx": {
          "name": "position_paper_scores_unique_idx",
          "columns": [
            {
              "expression": "committee_id",
              "isExpression": false,
              "asc": true,
              "nulls": "last"
            },
            {
              "expression": "delegate_id",
              "isExpression": false,
              "asc": true,
              "nulls": "last"
            }
          ],
          "isUnique": true,
          "concurrently": false,
          "method": "btree",
          "with": {}
        }
      },
      "foreignKeys": {
        "position_paper_scores_committee_id_committees_id_fk": {
          "name": "position_paper_scores_committee_id_committees_id_fk",
          "tableFrom": "position_paper_scores",
          "tableTo": "committees",
          "columnsFrom": [
            "committee_id"
          ],
          "columnsTo": [
            "id"
          ],
          "onDelete": "cascade",
          "onUpdate": "no action"
        }
      },
      "compositePrimaryKeys": {},
      "uniqueConstraints": {},
      "policies": {},
      "checkConstraints": {},
      "isRLSEnabled": false
    },
    "public.roll_call_attendance_events": {
      "name": "roll_call_attendance_events",
      "schema": "",
      "columns": {
        "id": {
          "name": "id",
          "type": "uuid",
          "primaryKey": true,
          "notNull": true,
          "default": "gen_random_uuid()"
        },
        "session_id": {
          "name": "session_id",
          "type": "uuid",
          "primaryKey": false,
          "notNull": true
        },
        "delegate_id": {
          "name": "delegate_id",
          "type": "text",
          "primaryKey": false,
          "notNull": true
        },
        "status": {
          "name": "status",
          "type": "text",
          "primaryKey": false,
          "notNull": true
        },
        "recorded_at": {
          "name": "recorded_at",
          "type": "timestamp with time zone",
          "primaryKey": false,
          "notNull": true,
          "default": "now()"
        },
        "recorded_by": {
          "name": "recorded_by",
          "type": "uuid",
          "primaryKey": false,
          "notNull": false
        }
      },
      "indexes": {
        "roll_call_attendance_lookup_idx": {
          "name": "roll_call_attendance_lookup_idx",
          "columns": [
            {
              "expression": "session_id",
              "isExpression": false,
              "asc": true,
              "nulls": "last"
            },
            {
              "expression": "delegate_id",
              "isExpression": false,
              "asc": true,
              "nulls": "last"
            },
            {
              "expression": "recorded_at",
              "isExpression": false,
              "asc": true,
              "nulls": "last"
            }
          ],
          "isUnique": false,
          "concurrently": false,
          "method": "btree",
          "with": {}
        }
      },
      "foreignKeys": {
        "roll_call_attendance_events_session_id_roll_call_sessions_id_fk": {
          "name": "roll_call_attendance_events_session_id_roll_call_sessions_id_fk",
          "tableFrom": "roll_call_attendance_events",
          "tableTo": "roll_call_sessions",
          "columnsFrom": [
            "session_id"
          ],
          "columnsTo": [
            "id"
          ],
          "onDelete": "cascade",
          "onUpdate": "no action"
        }
      },
      "compositePrimaryKeys": {},
      "uniqueConstraints": {},
      "policies": {},
      "checkConstraints": {},
      "isRLSEnabled": false
    },
    "public.roll_call_sessions": {
      "name": "roll_call_sessions",
      "schema": "",
      "columns": {
        "id": {
          "name": "id",
          "type": "uuid",
          "primaryKey": true,
          "notNull": true
        },
        "committee_id": {
          "name": "committee_id",
          "type": "uuid",
          "primaryKey": false,
          "notNull": true
        },
        "label": {
          "name": "label",
          "type": "text",
          "primaryKey": false,
          "notNull": true
        },
        "timestamp": {
          "name": "timestamp",
          "type": "text",
          "primaryKey": false,
          "notNull": true
        },
        "quorum_met": {
          "name": "quorum_met",
          "type": "boolean",
          "primaryKey": false,
          "notNull": true,
          "default": false
        },
        "version": {
          "name": "version",
          "type": "integer",
          "primaryKey": false,
          "notNull": true,
          "default": 0
        },
        "created_at": {
          "name": "created_at",
          "type": "timestamp with time zone",
          "primaryKey": false,
          "notNull": true,
          "default": "now()"
        }
      },
      "indexes": {
        "roll_call_sessions_committee_idx": {
          "name": "roll_call_sessions_committee_idx",
          "columns": [
            {
              "expression": "committee_id",
              "isExpression": false,
              "asc": true,
              "nulls": "last"
            },
            {
              "expression": "created_at",
              "isExpression": false,
              "asc": true,
              "nulls": "last"
            }
          ],
          "isUnique": false,
          "concurrently": false,
          "method": "btree",
          "with": {}
        }
      },
      "foreignKeys": {
        "roll_call_sessions_committee_id_committees_id_fk": {
          "name": "roll_call_sessions_committee_id_committees_id_fk",
          "tableFrom": "roll_call_sessions",
          "tableTo": "committees",
          "columnsFrom": [
            "committee_id"
          ],
          "columnsTo": [
            "id"
          ],
          "onDelete": "cascade",
          "onUpdate": "no action"
        }
      },
      "compositePrimaryKeys": {},
      "uniqueConstraints": {},
      "policies": {},
      "checkConstraints": {},
      "isRLSEnabled": false
    },
    "public.rubric_scores": {
      "name": "rubric_scores",
      "schema": "",
      "columns": {
        "id": {
          "name": "id",
          "type": "uuid",
          "primaryKey": true,
          "notNull": true,
          "default": "gen_random_uuid()"
        },
        "committee_id": {
          "name": "committee_id",
          "type": "uuid",
          "primaryKey": false,
          "notNull": true
        },
        "role": {
          "name": "role",
          "type": "text",
          "primaryKey": false,
          "notNull": true
        },
        "delegate_id": {
          "name": "delegate_id",
          "type": "text",
          "primaryKey": false,
          "notNull": true
        },
        "data": {
          "name": "data",
          "type": "jsonb",
          "primaryKey": false,
          "notNull": true
        },
        "version": {
          "name": "version",
          "type": "integer",
          "primaryKey": false,
          "notNull": true,
          "default": 0
        },
        "created_at": {
          "name": "created_at",
          "type": "timestamp with time zone",
          "primaryKey": false,
          "notNull": true,
          "default": "now()"
        }
      },
      "indexes": {
        "rubric_scores_unique_idx": {
          "name": "rubric_scores_unique_idx",
          "columns": [
            {
              "expression": "committee_id",
              "isExpression": false,
              "asc": true,
              "nulls": "last"
            },
            {
              "expression": "role",
              "isExpression": false,
              "asc": true,
              "nulls": "last"
            },
            {
              "expression": "delegate_id",
              "isExpression": false,
              "asc": true,
              "nulls": "last"
            }
          ],
          "isUnique": true,
          "concurrently": false,
          "method": "btree",
          "with": {}
        }
      },
      "foreignKeys": {
        "rubric_scores_committee_id_committees_id_fk": {
          "name": "rubric_scores_committee_id_committees_id_fk",
          "tableFrom": "rubric_scores",
          "tableTo": "committees",
          "columnsFrom": [
            "committee_id"
          ],
          "columnsTo": [
            "id"
          ],
          "onDelete": "cascade",
          "onUpdate": "no action"
        }
      },
      "compositePrimaryKeys": {},
      "uniqueConstraints": {},
      "policies": {},
      "checkConstraints": {
        "rubric_scores_role_check": {
          "name": "rubric_scores_role_check",
          "value": "\"rubric_scores\".\"role\" IN ('judge', 'dais')"
        }
      },
      "isRLSEnabled": false
    },
    "public.speaking_events": {
      "name": "speaking_events",
      "schema": "",
      "columns": {
        "id": {
          "name": "id",
          "type": "uuid",
          "primaryKey": true,
          "notNull": true
        },
        "committee_id": {
          "name": "committee_id",
          "type": "uuid",
          "primaryKey": false,
          "notNull": true
        },
        "data": {
          "name": "data",
          "type": "jsonb",
          "primaryKey": false,
          "notNull": true
        },
        "created_at": {
          "name": "created_at",
          "type": "timestamp with time zone",
          "primaryKey": false,
          "notNull": true,
          "default": "now()"
        }
      },
      "indexes": {
        "speaking_events_committee_idx": {
          "name": "speaking_events_committee_idx",
          "columns": [
            {
              "expression": "committee_id",
              "isExpression": false,
              "asc": true,
              "nulls": "last"
            },
            {
              "expression": "created_at",
              "isExpression": false,
              "asc": true,
              "nulls": "last"
            }
          ],
          "isUnique": false,
          "concurrently": false,
          "method": "btree",
          "with": {}
        }
      },
      "foreignKeys": {
        "speaking_events_committee_id_committees_id_fk": {
          "name": "speaking_events_committee_id_committees_id_fk",
          "tableFrom": "speaking_events",
          "tableTo": "committees",
          "columnsFrom": [
            "committee_id"
          ],
          "columnsTo": [
            "id"
          ],
          "onDelete": "cascade",
          "onUpdate": "no action"
        }
      },
      "compositePrimaryKeys": {},
      "uniqueConstraints": {},
      "policies": {},
      "checkConstraints": {},
      "isRLSEnabled": false
    },
    "public.users": {
      "name": "users",
      "schema": "",
      "columns": {
        "id": {
          "name": "id",
          "type": "uuid",
          "primaryKey": true,
          "notNull": true,
          "default": "gen_random_uuid()"
        },
        "conference_id": {
          "name": "conference_id",
          "type": "uuid",
          "primaryKey": false,
          "notNull": true
        },
        "username": {
          "name": "username",
          "type": "text",
          "primaryKey": false,
          "notNull": true
        },
        "password_hash": {
          "name": "password_hash",
          "type": "text",
          "primaryKey": false,
          "notNull": true
        },
        "role": {
          "name": "role",
          "type": "text",
          "primaryKey": false,
          "notNull": true
        },
        "permissions": {
          "name": "permissions",
          "type": "jsonb",
          "primaryKey": false,
          "notNull": true,
          "default": "'[]'::jsonb"
        },
        "committee_id": {
          "name": "committee_id",
          "type": "uuid",
          "primaryKey": false,
          "notNull": false,
          "default": "NULL"
        },
        "display_name": {
          "name": "display_name",
          "type": "text",
          "primaryKey": false,
          "notNull": true,
          "default": "''"
        },
        "created_at": {
          "name": "created_at",
          "type": "timestamp with time zone",
          "primaryKey": false,
          "notNull": true,
          "default": "now()"
        }
      },
      "indexes": {},
      "foreignKeys": {
        "users_conference_id_conferences_id_fk": {
          "name": "users_conference_id_conferences_id_fk",
          "tableFrom": "users",
          "tableTo": "conferences",
          "columnsFrom": [
            "conference_id"
          ],
          "columnsTo": [
            "id"
          ],
          "onDelete": "cascade",
          "onUpdate": "no action"
        },
        "users_committee_id_committees_id_fk": {
          "name": "users_committee_id_committees_id_fk",
          "tableFrom": "users",
          "tableTo": "committees",
          "columnsFrom": [
            "committee_id"
          ],
          "columnsTo": [
            "id"
          ],
          "onDelete": "set null",
          "onUpdate": "no action"
        }
      },
      "compositePrimaryKeys": {},
      "uniqueConstraints": {
        "users_username_unique": {
          "name": "users_username_unique",
          "nullsNotDistinct": false,
          "columns": [
            "username"
          ]
        }
      },
      "policies": {},
      "checkConstraints": {
        "role_check": {
          "name": "role_check",
          "value": "\"users\".\"role\" IN ('admin', 'chair', 'registrar', 'custom')"
        }
      },
      "isRLSEnabled": false
    }
  },
  "enums": {},
  "schemas": {},
  "sequences": {},
  "roles": {},
  "policies": {},
  "views": {},
  "_meta": {
    "columns": {},
    "schemas": {},
    "tables": {}
  }
}